{
 "custom_fields": [
  {
   "_assign": null, 
   "_comments": null, 
   "_liked_by": null, 
   "_user_tags": null, 
   "allow_on_submit": 0, 
   "bold": 0, 
   "collapsible": 0, 
   "collapsible_depends_on": null, 
   "columns": 0, 
   "creation": "2018-05-31 18:27:01.917670", 
   "default": null, 
   "depends_on": null, 
   "description": null, 
   "docstatus": 0, 
   "dt": "Quotation Detail Item", 
   "fieldname": "parent_uom", 
   "fieldtype": "Link", 
   "hidden": 0, 
   "idx": 3, 
   "ignore_user_permissions": 0, 
   "ignore_xss_filter": 0, 
   "in_global_search": 0, 
   "in_list_view": 0, 
   "in_standard_filter": 0, 
   "insert_after": "parent_qty", 
   "label": "Parent UOM", 
   "modified": "2018-05-31 18:27:01.917670", 
   "modified_by": "Administrator", 
   "name": "Quotation Detail Item-parent_uom", 
   "no_copy": 0, 
   "options": "UOM", 
   "owner": "Administrator", 
   "parent": null, 
   "parentfield": null, 
   "parenttype": null, 
   "permlevel": 0, 
   "precision": "", 
   "print_hide": 0, 
   "print_hide_if_no_value": 0, 
   "print_width": null, 
   "read_only": 0, 
   "report_hide": 0, 
   "reqd": 0, 
   "search_index": 0, 
   "unique": 0, 
   "width": null
  }, 
  {
   "_assign": null, 
   "_comments": null, 
   "_liked_by": null, 
   "_user_tags": null, 
   "allow_on_submit": 0, 
   "bold": 0, 
   "collapsible": 0, 
   "collapsible_depends_on": null, 
   "columns": 0, 
   "creation": "2018-05-31 13:07:19.372268", 
   "default": null, 
   "depends_on": null, 
   "description": null, 
   "docstatus": 0, 
   "dt": "Quotation Detail Item", 
   "fieldname": "parent_qty", 
   "fieldtype": "Float", 
   "hidden": 0, 
   "idx": 3, 
   "ignore_user_permissions": 0, 
   "ignore_xss_filter": 0, 
   "in_global_search": 0, 
   "in_list_view": 0, 
   "in_standard_filter": 0, 
   "insert_after": "parent_bom", 
   "label": "Parent Qty", 
   "modified": "2018-05-31 13:07:19.372268", 
   "modified_by": "Administrator", 
   "name": "Quotation Detail Item-parent_qty", 
   "no_copy": 0, 
   "options": null, 
   "owner": "Administrator", 
   "parent": null, 
   "parentfield": null, 
   "parenttype": null, 
   "permlevel": 0, 
   "precision": "", 
   "print_hide": 0, 
   "print_hide_if_no_value": 0, 
   "print_width": null, 
   "read_only": 0, 
   "report_hide": 0, 
   "reqd": 0, 
   "search_index": 0, 
   "unique": 0, 
   "width": null
  }, 
  {
   "_assign": null, 
   "_comments": null, 
   "_liked_by": null, 
   "_user_tags": null, 
   "allow_on_submit": 0, 
   "bold": 0, 
   "collapsible": 0, 
   "collapsible_depends_on": null, 
   "columns": 2, 
   "creation": "2018-05-21 11:49:39.459279", 
   "default": null, 
   "depends_on": null, 
   "description": null, 
   "docstatus": 0, 
   "dt": "Quotation Detail Item", 
   "fieldname": "parent_bom", 
   "fieldtype": "Data", 
   "hidden": 0, 
   "idx": 2, 
   "ignore_user_permissions": 0, 
   "ignore_xss_filter": 0, 
   "in_global_search": 0, 
   "in_list_view": 1, 
   "in_standard_filter": 0, 
   "insert_after": "bom_id", 
   "label": "Parent BOM", 
   "modified": "2018-05-21 11:49:39.459279", 
   "modified_by": "Administrator", 
   "name": "Quotation Detail Item-parent_bom", 
   "no_copy": 0, 
   "options": null, 
   "owner": "Administrator", 
   "parent": null, 
   "parentfield": null, 
   "parenttype": null, 
   "permlevel": 0, 
   "precision": "", 
   "print_hide": 0, 
   "print_hide_if_no_value": 0, 
   "print_width": null, 
   "read_only": 0, 
   "report_hide": 0, 
   "reqd": 0, 
   "search_index": 0, 
   "unique": 0, 
   "width": null
  }
 ], 
 "custom_perms": [], 
 "doctype": "Quotation Detail Item", 
 "property_setters": [
  {
   "_assign": null, 
   "_comments": null, 
   "_liked_by": null, 
   "_user_tags": null, 
   "creation": "2018-05-31 18:27:01.838305", 
   "default_value": null, 
   "doc_type": "Quotation Detail Item", 
   "docstatus": 0, 
   "doctype_or_field": "DocType", 
   "field_name": null, 
   "idx": 0, 
   "modified": "2018-05-31 18:27:01.838305", 
   "modified_by": "Administrator", 
   "name": "Quotation Detail Item-read_only_onload", 
   "owner": "Administrator", 
   "parent": null, 
   "parentfield": null, 
   "parenttype": null, 
   "property": "read_only_onload", 
   "property_type": "Check", 
   "value": null
  }, 
  {
   "_assign": null, 
   "_comments": null, 
   "_liked_by": null, 
   "_user_tags": null, 
   "creation": "2018-05-21 11:57:10.787287", 
   "default_value": null, 
   "doc_type": "Quotation Detail Item", 
   "docstatus": 0, 
   "doctype_or_field": "DocField", 
   "field_name": "rate", 
   "idx": 0, 
   "modified": "2018-05-21 11:57:10.787287", 
   "modified_by": "Administrator", 
   "name": "Quotation Detail Item-rate-columns", 
   "owner": "Administrator", 
   "parent": null, 
   "parentfield": null, 
   "parenttype": null, 
   "property": "columns", 
   "property_type": "Int", 
   "value": "1"
  }, 
  {
   "_assign": null, 
   "_comments": null, 
   "_liked_by": null, 
   "_user_tags": null, 
   "creation": "2018-05-21 11:55:54.731175", 
   "default_value": null, 
   "doc_type": "Quotation Detail Item", 
   "docstatus": 0, 
   "doctype_or_field": "DocField", 
   "field_name": "qty", 
   "idx": 0, 
   "modified": "2018-05-21 11:55:54.731175", 
   "modified_by": "Administrator", 
   "name": "Quotation Detail Item-qty-columns", 
   "owner": "Administrator", 
   "parent": null, 
   "parentfield": null, 
   "parenttype": null, 
   "property": "columns", 
   "property_type": "Int", 
   "value": "1"
  }, 
  {
   "_assign": null, 
   "_comments": null, 
   "_liked_by": null, 
   "_user_tags": null, 
   "creation": "2018-05-21 11:55:23.345622", 
   "default_value": null, 
   "doc_type": "Quotation Detail Item", 
   "docstatus": 0, 
   "doctype_or_field": "DocField", 
   "field_name": "display_name", 
   "idx": 0, 
   "modified": "2018-05-21 11:55:23.345622", 
   "modified_by": "Administrator", 
   "name": "Quotation Detail Item-display_name-columns", 
   "owner": "Administrator", 
   "parent": null, 
   "parentfield": null, 
   "parenttype": null, 
   "property": "columns", 
   "property_type": "Int", 
   "value": "4"
  }, 
  {
   "_assign": null, 
   "_comments": null, 
   "_liked_by": null, 
   "_user_tags": null, 
   "creation": "2018-05-21 11:53:23.223616", 
   "default_value": null, 
   "doc_type": "Quotation Detail Item", 
   "docstatus": 0, 
   "doctype_or_field": "DocField", 
   "field_name": "item_code", 
   "idx": 0, 
   "modified": "2018-05-21 11:53:23.223616", 
   "modified_by": "Administrator", 
   "name": "Quotation Detail Item-item_code-in_list_view", 
   "owner": "Administrator", 
   "parent": null, 
   "parentfield": null, 
   "parenttype": null, 
   "property": "in_list_view", 
   "property_type": "Check", 
   "value": "0"
  }, 
  {
   "_assign": null, 
   "_comments": null, 
   "_liked_by": null, 
   "_user_tags": null, 
   "creation": "2018-05-21 11:53:23.217927", 
   "default_value": null, 
   "doc_type": "Quotation Detail Item", 
   "docstatus": 0, 
   "doctype_or_field": "DocField", 
   "field_name": "bom_id", 
   "idx": 0, 
   "modified": "2018-05-21 11:53:23.217927", 
   "modified_by": "Administrator", 
   "name": "Quotation Detail Item-bom_id-in_list_view", 
   "owner": "Administrator", 
   "parent": null, 
   "parentfield": null, 
   "parenttype": null, 
   "property": "in_list_view", 
   "property_type": "Check", 
   "value": "0"
  }
 ], 
 "sync_on_migrate": 1
}