{
 "custom_fields": [], 
 "custom_perms": [], 
 "doctype": "Sales Order Item", 
 "property_setters": [
  {
   "_assign": null, 
   "_comments": null, 
   "_liked_by": null, 
   "_user_tags": null, 
   "creation": "2018-04-27 09:00:01.406492", 
   "default_value": null, 
   "doc_type": "Sales Order Item", 
   "docstatus": 0, 
   "doctype_or_field": "DocField", 
   "field_name": "pricing_rule", 
   "idx": 0, 
   "modified": "2018-04-27 09:00:01.406492", 
   "modified_by": "Administrator", 
   "name": "Sales Order Item-pricing_rule-print_hide", 
   "owner": "Administrator", 
   "parent": null, 
   "parentfield": null, 
   "parenttype": null, 
   "property": "print_hide", 
   "property_type": "Check", 
   "value": "1"
  }, 
  {
   "_assign": null, 
   "_comments": null, 
   "_liked_by": null, 
   "_user_tags": null, 
   "creation": "2018-04-27 09:00:01.353067", 
   "default_value": null, 
   "doc_type": "Sales Order Item", 
   "docstatus": 0, 
   "doctype_or_field": "DocType", 
   "field_name": null, 
   "idx": 0, 
   "modified": "2018-04-27 09:00:01.353067", 
   "modified_by": "Administrator", 
   "name": "Sales Order Item-read_only_onload", 
   "owner": "Administrator", 
   "parent": null, 
   "parentfield": null, 
   "parenttype": null, 
   "property": "read_only_onload", 
   "property_type": "Check", 
   "value": null
  }
 ], 
 "sync_on_migrate": 1
}